croustiistuff/__init__.py
croustiistuff/logger.py
croustiistuff/solver.py
croustiistuff-0.1.5.dist-info/METADATA
croustiistuff-0.1.5.dist-info/WHEEL
croustiistuff-0.1.5.dist-info/top_level.txt
croustiistuff-0.1.5.dist-info/RECORD
